[
  {
    "specialities": "AI1"
  },
  {
    "id": "S5",
    "courses": [
      {
        "id": "UEF1-ARCH",
        "title": "Architecture et administration des BDD",
        "description": "Architecture and administration of databases.",
        "coeff": 4
      },
      {
        "id": "UEF1-COMP",
        "title": "Compilation",
        "description": "Compiler construction.",
        "coeff": 4
      },
      {
        "id": "UEF2-PLD",
        "title": "Programmation Linéaire et Dynamique",
        "description": "Linear and dynamic programming.",
        "coeff": 4
      },
      {
        "id": "UEF2-GL",
        "title": "Génie logiciel",
        "description": "Software engineering.",
        "coeff": 4
      },
      {
        "id": "UED1-IA",
        "title": "Fondements de l’IA",
        "description": "Foundations of artificial intelligence.",
        "coeff": 2
      },
      {
        "id": "UET1-OPT",
        "title": "Module optionnel (ex: Interface Homme Machine, Conception de jeux vidéo)",
        "description": "Optional module (e.g., Human-Computer Interaction, Game Design).",
        "coeff": 2
      }
    ]
  },
  {
    "id": "S6",
    "courses": [
      {
        "id": "UEF1-BDR",
        "title": "Gestion des bases de données réparties",
        "description": "Distributed database management.",
        "coeff": 3
      },
      {
        "id": "UEF1-SE",
        "title": "Système d’Exploitation : Synchronisation et Communication",
        "description": "Operating Systems: Synchronization and Communication.",
        "coeff": 4
      },
      {
        "id": "UEF1-GP",
        "title": "Gestion de projets",
        "description": "Project management.",
        "coeff": 3
      },
      {
        "id": "UEF2-PWEB",
        "title": "Programmation WEB",
        "description": "Web programming.",
        "coeff": 4
      },
      {
        "id": "UEF2-AN2",
        "title": "Analyse numérique 2",
        "description": "Numerical analysis 2.",
        "coeff": 4
      },
      {
        "id": "UED1-SEC",
        "title": "Introduction à la sécurité informatique",
        "description": "Introduction to computer security.",
        "coeff": 2
      },
      {
        "id": "UET1-ETH",
        "title": "Éthique de l’IA",
        "description": "AI ethics.",
        "coeff": 2
      }
    ]
  }
]